{"images":[{"media_url":"https://scontent.cdninstagram.com/v/t51.29350-15/167248823_499924504344302_8618949318157703961_n.jpg?_nc_cat=108&ccb=1-3&_nc_sid=8ae9d6&_nc_ohc=oSpImS9vIwwAX9vg26l&_nc_ht=scontent.cdninstagram.com&oh=608b47cad28a4ebcaf5ee2192c4f3fba&oe=609F8962","username":"shopycode_agency","permalink":"https://www.instagram.com/p/CNAhVZJDH70/","id":"17862973325405561"},{"media_url":"https://scontent.cdninstagram.com/v/t51.29350-15/166736257_895469937693260_3229685899576369681_n.jpg?_nc_cat=102&ccb=1-3&_nc_sid=8ae9d6&_nc_ohc=yQKCoMG8RGEAX-XluSX&_nc_ht=scontent.cdninstagram.com&oh=c0c1f7354a181609bb4dfc9a9e0debc2&oe=609E56DE","username":"shopycode_agency","permalink":"https://www.instagram.com/p/CNAhHKvDCQx/","id":"17911547248684355"},{"caption":"Development","media_url":"https://scontent.cdninstagram.com/v/t51.29350-15/166013402_2175900722543319_1577970496890816868_n.jpg?_nc_cat=104&ccb=1-3&_nc_sid=8ae9d6&_nc_ohc=L1ekF-7xZd8AX9LJ4Tm&_nc_ht=scontent.cdninstagram.com&oh=236af0b483d555184ac86497a4e12d46&oe=609DD039","username":"shopycode_agency","permalink":"https://www.instagram.com/p/CNCtQJYDEP8/","id":"17880239450233594"},{"caption":"Development","media_url":"https://scontent.cdninstagram.com/v/t51.29350-15/167033177_359723208621264_2491403724163586197_n.jpg?_nc_cat=107&ccb=1-3&_nc_sid=8ae9d6&_nc_ohc=OsFahz0W3nUAX8F7eCz&_nc_ht=scontent.cdninstagram.com&oh=aa1224b0455ffca6fbe1192850fd61b1&oe=60A04CB3","username":"shopycode_agency","permalink":"https://www.instagram.com/p/CNCtGNCjNk5/","id":"18103532410241806"},{"caption":"Development","media_url":"https://scontent.cdninstagram.com/v/t51.29350-15/166831683_468534567919680_5768319707603732846_n.jpg?_nc_cat=103&ccb=1-3&_nc_sid=8ae9d6&_nc_ohc=Z-ORwNBxMxoAX9RYJrq&_nc_ht=scontent.cdninstagram.com&oh=34f296e43eb48a19f5a96cd1b80c7d3b&oe=609FE9CF","username":"shopycode_agency","permalink":"https://www.instagram.com/p/CNCtW9_DBh6/","id":"17864731793385079"},{"media_url":"https://scontent.cdninstagram.com/v/t51.29350-15/165983975_556815991963787_6515371334988108703_n.jpg?_nc_cat=103&ccb=1-3&_nc_sid=8ae9d6&_nc_ohc=QWt1CaqEgnoAX9Q7gj-&_nc_oc=AQkkbOpeBabMAo-m9nHKBJIR8JWD5xknHw57P0TyhxU0F86kXYSLPGww8r7iohMCVdg&_nc_ht=scontent.cdninstagram.com&oh=268af032a6aade10bd13e7492604ba1d&oe=609EF2A5","username":"shopycode_agency","permalink":"https://www.instagram.com/p/CNAhTzvDP3B/","id":"17883017858165956"},{"caption":"Development","media_url":"https://scontent.cdninstagram.com/v/t51.29350-15/166600393_3849365211815465_8889752038004110654_n.jpg?_nc_cat=107&ccb=1-3&_nc_sid=8ae9d6&_nc_ohc=XRu-n03yOXwAX-JeqMc&_nc_ht=scontent.cdninstagram.com&oh=05877d54df88466f5b00960c4e9b9a19&oe=609D6CE0","username":"shopycode_agency","permalink":"https://www.instagram.com/p/CNCtgyvDGmL/","id":"17897301412902364"},{"caption":"Development","media_url":"https://scontent.cdninstagram.com/v/t51.29350-15/166449869_772674497003570_562509928985277039_n.jpg?_nc_cat=102&ccb=1-3&_nc_sid=8ae9d6&_nc_ohc=hv0dRtMKED0AX9mU61h&_nc_ht=scontent.cdninstagram.com&oh=319062831ab220ee35c9c1e1632555b6&oe=609FFA53","username":"shopycode_agency","permalink":"https://www.instagram.com/p/CNCp8ekDF7g/","id":"18000154081317157"}]}